{
    "execution_summary": "Phase 3C Severity Scoring successfully integrated sentiment analysis with LDA taxonomy.",
    "methodology": {
        "formula": "severity_score = freq * negative_ratio * mean_neg_conf * (1 + high_conf_ratio)",
        "adjustment": "Neutral sentiments were not discarded but weighted zero for severity calculation. High confidence negatives (>0.8) applied a multiplier effect to penalize critical failures."
    },
    "key_findings": {
        "most_severe_barrier": "TB-1 Cognitive Difficulty",
        "least_severe_barrier": "TB-6 Cost / Affordability Barrier",
        "total_critical_barriers_detected": 1881
    }
}